astri_migration_tool/__init__.py
astri_migration_tool/alpr/__init__.py
astri_migration_tool/alpr/layout_generator/__init__.py
astri_migration_tool/alpr/netlist_loader/__init__.py
astri_migration_tool/alpr/netlist_loader/read_spice.py
astri_migration_tool/alpr/pdk_loader/__init__.py
astri_migration_tool/alpr/pr_engine/__init__.py
astri_migration_tool/alpr/schema/README.md
astri_migration_tool/alpr/schema/__init__.py
astri_migration_tool/alpr/schema/checker.py
astri_migration_tool/alpr/schema/constraint.py
astri_migration_tool/alpr/schema/gen_dot.py
astri_migration_tool/alpr/schema/graph.py
astri_migration_tool/alpr/schema/hacks.py
astri_migration_tool/alpr/schema/instance.py
astri_migration_tool/alpr/schema/library.py
astri_migration_tool/alpr/schema/model.py
astri_migration_tool/alpr/schema/parser.py
astri_migration_tool/alpr/schema/pdk.py
astri_migration_tool/alpr/schema/subcircuit.py
astri_migration_tool/alpr/schema/transistor.py
astri_migration_tool/alpr/schema/translator.py
astri_migration_tool/alpr/schema/types.py
astri_migration_tool/alpr/schema/visitor.py
astri_migration_tool/alpr/utils/__init__.py
astri_migration_tool/alpr/utils/fileio.py
astri_migration_tool/alpr/utils/logging.py
astri_migration_tool/requirements.txt
astri_migration_tool-0.1.3.dist-info/METADATA
astri_migration_tool-0.1.3.dist-info/WHEEL
astri_migration_tool-0.1.3.dist-info/RECORD
